jack_srs_fleet_manager/__init__.py
jack_srs_fleet_manager-0.1.0.dist-info/METADATA
jack_srs_fleet_manager-0.1.0.dist-info/WHEEL
jack_srs_fleet_manager-0.1.0.dist-info/RECORD
